rich_text_renderer/__init__.py
rich_text_renderer/base_node_renderer.py
rich_text_renderer/block_renderers.py
rich_text_renderer/document_renderers.py
rich_text_renderer/null_renderer.py
rich_text_renderer/rich_text_renderer.py
rich_text_renderer/text_renderers.py
rich_text_renderer-0.2.8.dist-info/LICENSE
rich_text_renderer-0.2.8.dist-info/METADATA
rich_text_renderer-0.2.8.dist-info/WHEEL
rich_text_renderer-0.2.8.dist-info/top_level.txt
rich_text_renderer-0.2.8.dist-info/RECORD
